odoo/addons/company_dependent_flag/README.rst
odoo/addons/company_dependent_flag/__init__.py
odoo/addons/company_dependent_flag/__manifest__.py
odoo/addons/company_dependent_flag/demo/__init__.py
odoo/addons/company_dependent_flag/demo/partner.py
odoo/addons/company_dependent_flag/i18n/company_dependent_flag.pot
odoo/addons/company_dependent_flag/i18n/es.po
odoo/addons/company_dependent_flag/i18n/it.po
odoo/addons/company_dependent_flag/models/__init__.py
odoo/addons/company_dependent_flag/models/base.py
odoo/addons/company_dependent_flag/readme/CONTRIBUTORS.rst
odoo/addons/company_dependent_flag/readme/DESCRIPTION.rst
odoo/addons/company_dependent_flag/readme/ROADMAP.rst
odoo/addons/company_dependent_flag/static/description/demo.png
odoo/addons/company_dependent_flag/static/description/icon.png
odoo/addons/company_dependent_flag/static/description/index.html
odoo/addons/company_dependent_flag/tests/__init__.py
odoo/addons/company_dependent_flag/tests/test_module.py
odoo_addon_company_dependent_flag-16.0.1.0.2.dist-info/METADATA
odoo_addon_company_dependent_flag-16.0.1.0.2.dist-info/WHEEL
odoo_addon_company_dependent_flag-16.0.1.0.2.dist-info/top_level.txt
odoo_addon_company_dependent_flag-16.0.1.0.2.dist-info/RECORD
