Metadata-Version: 2.1
Name: odoo-addon-company-dependent-flag
Version: 16.0.1.0.2
Summary: Apply css style to company dependent fields
Home-page: https://github.com/OCA/multi-company
Author: Akretion,Odoo Community Association (OCA)
Author-email: support@odoo-community.org
License: AGPL-3
Platform: UNKNOWN
Classifier: Programming Language :: Python
Classifier: Framework :: Odoo
Classifier: Framework :: Odoo :: 16.0
Classifier: License :: OSI Approved :: GNU Affero General Public License v3
Requires-Python: >=3.10
Requires-Dist: odoo <16.1dev,>=16.0a
